MANIFEST.in
README.rst
requirements.txt
setup.py
genderator/__init__.py
genderator/parser.py
genderator.egg-info/PKG-INFO
genderator.egg-info/SOURCES.txt
genderator.egg-info/dependency_links.txt
genderator.egg-info/requires.txt
genderator.egg-info/top_level.txt
genderator/data/.DS_Store
genderator/data/name_surname_ratio.tsv
genderator/data/names_ine.tsv
genderator/data/surnames_ine.tsv