Metadata-Version: 1.1
Name: genderator
Version: 0.2.7.8
Summary: Python library to guess gender given a spanish full name
Home-page: https://github.com/davidmogar/genderator
Author: David Moreno-Garcia
Author-email: david.mogar@gmail.com
License: MIT
Download-URL: https://github.com/davidmogar/genderator/tarball/0.2.7.8
Keywords: gender,guess,spanish,name
Platform: UNKNOWN
Classifier: Development Status :: 4 - Beta
Classifier: Topic :: Software Development :: Libraries
Classifier: Intended Audience :: Developers
Classifier: Intended Audience :: Education
Classifier: Intended Audience :: Information Technology
Classifier: License :: OSI Approved :: MIT License
Classifier: Programming Language :: Python
Classifier: Programming Language :: Python :: 3
